gramps_gedcom7/__init__.py
gramps_gedcom7/citation.py
gramps_gedcom7/event.py
gramps_gedcom7/family.py
gramps_gedcom7/gedcom2xml.py
gramps_gedcom7/header.py
gramps_gedcom7/importer.py
gramps_gedcom7/individual.py
gramps_gedcom7/multimedia.py
gramps_gedcom7/note.py
gramps_gedcom7/process.py
gramps_gedcom7/repository.py
gramps_gedcom7/settings.py
gramps_gedcom7/source.py
gramps_gedcom7/streamlit_app.py
gramps_gedcom7/submitter.py
gramps_gedcom7/types.py
gramps_gedcom7/util.py
gramps_gedcom7/web.py
gramps_gedcom7-0.3.0.dist-info/licenses/LICENSE
gramps_gedcom7-0.3.0.dist-info/METADATA
gramps_gedcom7-0.3.0.dist-info/WHEEL
gramps_gedcom7-0.3.0.dist-info/top_level.txt
gramps_gedcom7-0.3.0.dist-info/RECORD
