Metadata-Version: 2.4
Name: gramps_gedcom7
Version: 0.3.0
Summary: A GEDCOM 7 support library for Gramps genealogy software
Author-email: David Straub <straub@protonmail.com>
License: MIT
Project-URL: Homepage, https://github.com/DavidMStraub/gramps-gedcom7
Requires-Python: >=3.10
License-File: LICENSE
Requires-Dist: gramps>=6.0.0
Requires-Dist: gedcom7>=0.4.0
Requires-Dist: click
Provides-Extra: streamlit
Requires-Dist: streamlit; extra == "streamlit"
Dynamic: license-file
